supercar_verilog/L74x86.sv
// Quadruple 2-input xor gates
module L74x86
  (
    // Gate 1
    input [1:0] i_g1,
    output o_g1,

    // Gate 2
    input [1:0] i_g2,
    output o_g2,
    
    // Gate 3
    input [1:0] i_g3,
    output o_g3,
    
    // Gate 4
    input [1:0] i_g4,
    output o_g4
  );

  assign o_g1 = ^i_g1;
  assign o_g2 = ^i_g2;
  assign o_g3 = ^i_g3;
  assign o_g4 = ^i_g4;

endmodule

supercar_verilog/L74x574.sv
// Octal 3 state non inverting D flip-flop
module L74x574 #(parameter INITIAL_VALUE = 8'h00)
  (
    input [7:0] i_data,
    input i_n_oe,
    input i_clk,
    inout [7:0] o_q
  );

  reg [7:0] r_data = INITIAL_VALUE;

  always @(posedge i_clk)
  begin
    r_data <= i_data;
  end

  assign o_q = i_n_oe ? 8'bZ : r_data;

endmodule

supercar_verilog/L74x154.sv
// 4-to-16 line decoder/demultiplexer
module L74x154
  (
    input [3:0] i_address,
    input i_n_en0,
    input i_n_en1,
    output [15:0] o_selection
  );

  assign o_selection = (i_n_en0 || i_n_en1) ? 16'hFFFF : ~(1'b1 << i_address);

endmodule

supercar_verilog/L74x283.sv
// 4-bit binary full adder with fast carry
module L74x283
  (
    input [3:0] i_a,
    input [3:0] i_b,
    input i_cin,
    output [3:0] o_s,
    output o_cout
  );

  reg [4:0] r_sum;


  assign r_sum = i_a + i_b + i_cin;
  assign o_s = r_sum;
  assign o_cout = r_sum[4];

endmodule

supercar_verilog/Supercar.sv
module SuperCar
  (
    input i_clk,
    output [15:0] o_selection
  );

  wire [3:0] w_sum_result;
  wire [7:0] w_led_address;
  wire [7:0] w_addend;
  wire w_neg_addend;
  wire w_addend_clk;

  wire w_u5_g2_out;
  wire w_u5_g3_out;

  wire [3:0] w_inverted_led_address;

  L74x283 U1 (
            .i_a(w_led_address[3:0]),
            .i_b(w_addend[3:0]),
            .i_cin(1'b0),
            .o_s(w_sum_result),
            .o_cout() // Left disconnected
          );

  L74x574 U2 (
            .i_data({4'h0, w_sum_result}),
            .i_clk(i_clk),
            .i_n_oe(1'b0),
            .o_q(w_led_address)
          );

  L74x154 U3 (
            .i_address(w_led_address[3:0]), // Only the 4 least significant bits are considered
            .i_n_en0(1'b0),
            .i_n_en1(1'b0),
            .o_selection(o_selection)
          );

  L74x574 #(.INITIAL_VALUE(8'hFF)) U4 (
            .i_data({4'h0, {3{o_selection[0]}}, 1'b1}),
            .i_clk(w_addend_clk),
            .i_n_oe(1'b0),
            .o_q(w_addend)
          );

  L74x86 U5 (
           .i_g1(2'b00), // Unused
           .o_g1(),
           .i_g2({o_selection[0], o_selection[$size(o_selection)-1]}),
           .o_g2(w_u5_g2_out),
           .i_g3({w_u5_g2_out, 1'b1}),
           .o_g3(w_u5_g3_out),
           .i_g4({w_u5_g3_out, 1'b1}),
           .o_g4(w_addend_clk)
         );

endmodule

supercar_verilog/testbench.vh
module Testbench_SuperCar();
  reg r_clk = 1'b0; // This will be used as clock
  wire [15:0] w_selection;
  integer i;

  // Use this always block to generate a clock
  // by inverting this register every time unit,
  // so a full clock cycle takes 2 time units
  always #1 r_clk <= !r_clk;

  SuperCar UUT (
    .i_clk(r_clk),
    .o_selection(w_selection)
  );

  initial
  begin
    $dumpfile("dump.vcd");
    $dumpvars;

    for(i = 0; i < 64; i = i + 1)
    begin
      @(posedge r_clk);
    end

    $display("Test Complete");
    $finish();
  end
endmodule

supercar_verilog/L74x21.sv
// 4-input 2 NAND gates
module L74x21
  (
    // Gate 1
    input [3:0] i_g1,
    output o_g1,

    // Gate 2
    input [3:0] i_g2,
    output o_g2
  );

  assign o_g1 = &i_g1;
  assign o_g2 = &i_g2;
endmodule

supercar_verilog/L74x04.sv
// 6 port hex inverter
module L74x04
  (
    // Gate 1
    input i_g1,
    output o_g1,

    // Gate 2
    input i_g2,
    output o_g2,
    
    // Gate 3
    input i_g3,
    output o_g3,
    
    // Gate 4
    input i_g4,
    output o_g4,
    
    // Gate 5
    input i_g5,
    output o_g5,
    
    // Gate 6
    input i_g6,
    output o_g6
  );

  assign o_g1 = ~i_g1;
  assign o_g2 = ~i_g2;
  assign o_g3 = ~i_g3;
  assign o_g4 = ~i_g4;
  assign o_g5 = ~i_g5;
  assign o_g6 = ~i_g6;

endmodule

supercar_verilog/L74x02.sv
// 2 port 4 NOR gates
module L74x02
  (
    // Gate 1
    input [1:0] i_g1,
    output o_g1,

    // Gate 2
    input [1:0] i_g2,
    output o_g2,
    
    // Gate 3
    input [1:0] i_g3,
    output o_g3,
    
    // Gate 4
    input [1:0] i_g4,
    output o_g4
  );

  assign o_g1 = ~|i_g1;
  assign o_g2 = ~|i_g2;
  assign o_g3 = ~|i_g3;
  assign o_g4 = ~|i_g4;

endmodule

supercar_verilog/dump.vcd
$date
	Mon Jan 29 08:05:22 2024
$end
$version
	Icarus Verilog
$end
$timescale
	1s
$end
$scope module L74x02 $end
$var wire 2 ! i_g1 [1:0] $end
$var wire 2 " i_g2 [1:0] $end
$var wire 2 # i_g3 [1:0] $end
$var wire 2 $ i_g4 [1:0] $end
$var wire 1 % o_g4 $end
$var wire 1 & o_g3 $end
$var wire 1 ' o_g2 $end
$var wire 1 ( o_g1 $end
$upscope $end
$scope module L74x04 $end
$var wire 1 ) i_g1 $end
$var wire 1 * i_g2 $end
$var wire 1 + i_g3 $end
$var wire 1 , i_g4 $end
$var wire 1 - i_g5 $end
$var wire 1 . i_g6 $end
$var wire 1 / o_g1 $end
$var wire 1 0 o_g2 $end
$var wire 1 1 o_g3 $end
$var wire 1 2 o_g4 $end
$var wire 1 3 o_g5 $end
$var wire 1 4 o_g6 $end
$upscope $end
$scope module L74x21 $end
$var wire 4 5 i_g1 [3:0] $end
$var wire 4 6 i_g2 [3:0] $end
$var wire 1 7 o_g2 $end
$var wire 1 8 o_g1 $end
$upscope $end
$scope module Testbench_SuperCar $end
$var wire 16 9 w_selection [15:0] $end
$var reg 1 : r_clk $end
$var integer 32 ; i [31:0] $end
$scope module UUT $end
$var wire 1 : i_clk $end
$var wire 1 < w_u5_g3_out $end
$var wire 1 = w_u5_g2_out $end
$var wire 4 > w_sum_result [3:0] $end
$var wire 8 ? w_led_address [7:0] $end
$var wire 1 @ w_addend_clk $end
$var wire 8 A w_addend [7:0] $end
$var wire 16 B o_selection [15:0] $end
$scope module U1 $end
$var wire 4 C i_a [3:0] $end
$var wire 4 D i_b [3:0] $end
$var wire 1 E i_cin $end
$var wire 5 F r_sum [4:0] $end
$var wire 4 G o_s [3:0] $end
$var wire 1 H o_cout $end
$upscope $end
$scope module U2 $end
$var wire 1 : i_clk $end
$var wire 8 I i_data [7:0] $end
$var wire 1 J i_n_oe $end
$var wire 8 K o_q [7:0] $end
$var parameter 8 L INITIAL_VALUE $end
$var reg 8 M r_data [7:0] $end
$upscope $end
$scope module U3 $end
$var wire 4 N i_address [3:0] $end
$var wire 1 O i_n_en0 $end
$var wire 1 P i_n_en1 $end
$var wire 16 Q o_selection [15:0] $end
$upscope $end
$scope module U4 $end
$var wire 8 R i_data [7:0] $end
$var wire 1 S i_n_oe $end
$var wire 8 T o_q [7:0] $end
$var wire 1 @ i_clk $end
$var parameter 8 U INITIAL_VALUE $end
$var reg 8 V r_data [7:0] $end
$upscope $end
$scope module U5 $end
$var wire 2 W i_g1 [1:0] $end
$var wire 2 X i_g2 [1:0] $end
$var wire 2 Y i_g3 [1:0] $end
$var wire 2 Z i_g4 [1:0] $end
$var wire 1 @ o_g4 $end
$var wire 1 < o_g3 $end
$var wire 1 = o_g2 $end
$var wire 1 [ o_g1 $end
$upscope $end
$upscope $end
$upscope $end
$enddefinitions $end
$comment Show the parameter values. $end
$dumpall
b11111111 U
b0 L
$end
#0
$dumpvars
0[
b1 Z
b11 Y
b1 X
b0 W
b1 V
b1 T
0S
b1 R
b1111111111111110 Q
0P
0O
b0 N
b0 M
b0 K
0J
b1 I
0H
b1 G
b1 F
0E
b1 D
b0 C
b1111111111111110 B
b1 A
1@
b0 ?
b1 >
1=
0<
b0 ;
0:
b1111111111111110 9
x8
x7
bz 6
bz 5
z4
z3
z2
z1
z0
z/
z.
z-
z,
z+
z*
z)
x(
x'
x&
x%
bz $
bz #
bz "
bz !
$end
#1
0@
b11 Z
1<
b1 Y
0=
b11 X
b1111 R
b1111111111111101 9
b1111111111111101 B
b1111111111111101 Q
b10 I
b10 >
b10 G
b1 N
b10 F
b1 C
b1 ?
b1 K
b1 M
b1 ;
1:
#2
0:
#3
b1111111111111011 9
b1111111111111011 B
b1111111111111011 Q
b11 I
b11 >
b11 G
b10 N
b11 F
b10 C
b10 ?
b10 K
b10 M
b10 ;
1:
#4
0:
#5
b1111111111110111 9
b1111111111110111 B
b1111111111110111 Q
b100 I
b100 >
b100 G
b11 N
b100 F
b11 C
b11 ?
b11 K
b11 M
b11 ;
1:
#6
0:
#7
b1111111111101111 9
b1111111111101111 B
b1111111111101111 Q
b101 I
b101 >
b101 G
b100 N
b101 F
b100 C
b100 ?
b100 K
b100 M
b100 ;
1:
#8
0:
#9
b1111111111011111 9
b1111111111011111 B
b1111111111011111 Q
b110 I
b110 >
b110 G
b101 N
b110 F
b101 C
b101 ?
b101 K
b101 M
b101 ;
1:
#10
0:
#11
b1111111110111111 9
b1111111110111111 B
b1111111110111111 Q
b111 I
b111 >
b111 G
b110 N
b111 F
b110 C
b110 ?
b110 K
b110 M
b110 ;
1:
#12
0:
#13
b1111111101111111 9
b1111111101111111 B
b1111111101111111 Q
b1000 I
b1000 >
b1000 G
b111 N
b1000 F
b111 C
b111 ?
b111 K
b111 M
b111 ;
1:
#14
0:
#15
b1111111011111111 9
b1111111011111111 B
b1111111011111111 Q
b1001 I
b1001 >
b1001 G
b1000 N
b1001 F
b1000 C
b1000 ?
b1000 K
b1000 M
b1000 ;
1:
#16
0:
#17
b1111110111111111 9
b1111110111111111 B
b1111110111111111 Q
b1010 I
b1010 >
b1010 G
b1001 N
b1010 F
b1001 C
b1001 ?
b1001 K
b1001 M
b1001 ;
1:
#18
0:
#19
b1111101111111111 9
b1111101111111111 B
b1111101111111111 Q
b1011 I
b1011 >
b1011 G
b1010 N
b1011 F
b1010 C
b1010 ?
b1010 K
b1010 M
b1010 ;
1:
#20
0:
#21
b1111011111111111 9
b1111011111111111 B
b1111011111111111 Q
b1100 I
b1100 >
b1100 G
b1011 N
b1100 F
b1011 C
b1011 ?
b1011 K
b1011 M
b1011 ;
1:
#22
0:
#23
b1110111111111111 9
b1110111111111111 B
b1110111111111111 Q
b1101 I
b1101 >
b1101 G
b1100 N
b1101 F
b1100 C
b1100 ?
b1100 K
b1100 M
b1100 ;
1:
#24
0:
#25
b1101111111111111 9
b1101111111111111 B
b1101111111111111 Q
b1110 I
b1110 >
b1110 G
b1101 N
b1110 F
b1101 C
b1101 ?
b1101 K
b1101 M
b1101 ;
1:
#26
0:
#27
b1011111111111111 9
b1011111111111111 B
b1011111111111111 Q
b1111 I
b1111 >
b1111 G
b1110 N
b1111 F
b1110 C
b1110 ?
b1110 K
b1110 M
b1110 ;
1:
#28
0:
#29
b1111 D
b1111 A
b1111 T
b1111 V
1@
b1 Z
0<
b11 Y
1=
b10 X
b111111111111111 9
b111111111111111 B
b111111111111111 Q
b1110 I
b1110 >
b1110 G
1H
b1111 N
b11110 F
b1111 C
b1111 ?
b1111 K
b1111 M
b1111 ;
1:
#30
0:
#31
0@
b11 Z
1<
b1 Y
0=
b11 X
b1011111111111111 9
b1011111111111111 B
b1011111111111111 Q
b1101 I
b1101 >
b1101 G
b1110 N
b11101 F
b1110 C
b1110 ?
b1110 K
b1110 M
b10000 ;
1:
#32
0:
#33
b1101111111111111 9
b1101111111111111 B
b1101111111111111 Q
b1100 I
b1100 >
b1100 G
b1101 N
b11100 F
b1101 C
b1101 ?
b1101 K
b1101 M
b10001 ;
1:
#34
0:
#35
b1110111111111111 9
b1110111111111111 B
b1110111111111111 Q
b1011 I
b1011 >
b1011 G
b1100 N
b11011 F
b1100 C
b1100 ?
b1100 K
b1100 M
b10010 ;
1:
#36
0:
#37
b1111011111111111 9
b1111011111111111 B
b1111011111111111 Q
b1010 I
b1010 >
b1010 G
b1011 N
b11010 F
b1011 C
b1011 ?
b1011 K
b1011 M
b10011 ;
1:
#38
0:
#39
b1111101111111111 9
b1111101111111111 B
b1111101111111111 Q
b1001 I
b1001 >
b1001 G
b1010 N
b11001 F
b1010 C
b1010 ?
b1010 K
b1010 M
b10100 ;
1:
#40
0:
#41
b1111110111111111 9
b1111110111111111 B
b1111110111111111 Q
b1000 I
b1000 >
b1000 G
b1001 N
b11000 F
b1001 C
b1001 ?
b1001 K
b1001 M
b10101 ;
1:
#42
0:
#43
b1111111011111111 9
b1111111011111111 B
b1111111011111111 Q
b111 I
b111 >
b111 G
b1000 N
b10111 F
b1000 C
b1000 ?
b1000 K
b1000 M
b10110 ;
1:
#44
0:
#45
b1111111101111111 9
b1111111101111111 B
b1111111101111111 Q
b110 I
b110 >
b110 G
b111 N
b10110 F
b111 C
b111 ?
b111 K
b111 M
b10111 ;
1:
#46
0:
#47
b1111111110111111 9
b1111111110111111 B
b1111111110111111 Q
b101 I
b101 >
b101 G
b110 N
b10101 F
b110 C
b110 ?
b110 K
b110 M
b11000 ;
1:
#48
0:
#49
b1111111111011111 9
b1111111111011111 B
b1111111111011111 Q
b100 I
b100 >
b100 G
b101 N
b10100 F
b101 C
b101 ?
b101 K
b101 M
b11001 ;
1:
#50
0:
#51
b1111111111101111 9
b1111111111101111 B
b1111111111101111 Q
b11 I
b11 >
b11 G
b100 N
b10011 F
b100 C
b100 ?
b100 K
b100 M
b11010 ;
1:
#52
0:
#53
b1111111111110111 9
b1111111111110111 B
b1111111111110111 Q
b10 I
b10 >
b10 G
b11 N
b10010 F
b11 C
b11 ?
b11 K
b11 M
b11011 ;
1:
#54
0:
#55
b1111111111111011 9
b1111111111111011 B
b1111111111111011 Q
b1 I
b1 >
b1 G
b10 N
b10001 F
b10 C
b10 ?
b10 K
b10 M
b11100 ;
1:
#56
0:
#57
b1111111111111101 9
b1111111111111101 B
b1111111111111101 Q
b0 I
b0 >
b0 G
b1 N
b10000 F
b1 C
b1 ?
b1 K
b1 M
b11101 ;
1:
#58
0:
#59
b1 D
b1 A
b1 T
b1 V
1@
b1 Z
0<
b11 Y
1=
b1 X
b1 R
b1111111111111110 9
b1111111111111110 B
b1111111111111110 Q
b1 I
b1 >
b1 G
0H
b0 N
b1 F
b0 C
b0 ?
b0 K
b0 M
b11110 ;
1:
#60
0:
#61
0@
b11 Z
1<
b1 Y
0=
b11 X
b1111 R
b1111111111111101 9
b1111111111111101 B
b1111111111111101 Q
b10 I
b10 >
b10 G
b1 N
b10 F
b1 C
b1 ?
b1 K
b1 M
b11111 ;
1:
#62
0:
#63
b1111111111111011 9
b1111111111111011 B
b1111111111111011 Q
b11 I
b11 >
b11 G
b10 N
b11 F
b10 C
b10 ?
b10 K
b10 M
b100000 ;
1:
#64
0:
#65
b1111111111110111 9
b1111111111110111 B
b1111111111110111 Q
b100 I
b100 >
b100 G
b11 N
b100 F
b11 C
b11 ?
b11 K
b11 M
b100001 ;
1:
#66
0:
#67
b1111111111101111 9
b1111111111101111 B
b1111111111101111 Q
b101 I
b101 >
b101 G
b100 N
b101 F
b100 C
b100 ?
b100 K
b100 M
b100010 ;
1:
#68
0:
#69
b1111111111011111 9
b1111111111011111 B
b1111111111011111 Q
b110 I
b110 >
b110 G
b101 N
b110 F
b101 C
b101 ?
b101 K
b101 M
b100011 ;
1:
#70
0:
#71
b1111111110111111 9
b1111111110111111 B
b1111111110111111 Q
b111 I
b111 >
b111 G
b110 N
b111 F
b110 C
b110 ?
b110 K
b110 M
b100100 ;
1:
#72
0:
#73
b1111111101111111 9
b1111111101111111 B
b1111111101111111 Q
b1000 I
b1000 >
b1000 G
b111 N
b1000 F
b111 C
b111 ?
b111 K
b111 M
b100101 ;
1:
#74
0:
#75
b1111111011111111 9
b1111111011111111 B
b1111111011111111 Q
b1001 I
b1001 >
b1001 G
b1000 N
b1001 F
b1000 C
b1000 ?
b1000 K
b1000 M
b100110 ;
1:
#76
0:
#77
b1111110111111111 9
b1111110111111111 B
b1111110111111111 Q
b1010 I
b1010 >
b1010 G
b1001 N
b1010 F
b1001 C
b1001 ?
b1001 K
b1001 M
b100111 ;
1:
#78
0:
#79
b1111101111111111 9
b1111101111111111 B
b1111101111111111 Q
b1011 I
b1011 >
b1011 G
b1010 N
b1011 F
b1010 C
b1010 ?
b1010 K
b1010 M
b101000 ;
1:
#80
0:
#81
b1111011111111111 9
b1111011111111111 B
b1111011111111111 Q
b1100 I
b1100 >
b1100 G
b1011 N
b1100 F
b1011 C
b1011 ?
b1011 K
b1011 M
b101001 ;
1:
#82
0:
#83
b1110111111111111 9
b1110111111111111 B
b1110111111111111 Q
b1101 I
b1101 >
b1101 G
b1100 N
b1101 F
b1100 C
b1100 ?
b1100 K
b1100 M
b101010 ;
1:
#84
0:
#85
b1101111111111111 9
b1101111111111111 B
b1101111111111111 Q
b1110 I
b1110 >
b1110 G
b1101 N
b1110 F
b1101 C
b1101 ?
b1101 K
b1101 M
b101011 ;
1:
#86
0:
#87
b1011111111111111 9
b1011111111111111 B
b1011111111111111 Q
b1111 I
b1111 >
b1111 G
b1110 N
b1111 F
b1110 C
b1110 ?
b1110 K
b1110 M
b101100 ;
1:
#88
0:
#89
b1111 D
b1111 A
b1111 T
b1111 V
1@
b1 Z
0<
b11 Y
1=
b10 X
b111111111111111 9
b111111111111111 B
b111111111111111 Q
b1110 I
b1110 >
b1110 G
1H
b1111 N
b11110 F
b1111 C
b1111 ?
b1111 K
b1111 M
b101101 ;
1:
#90
0:
#91
0@
b11 Z
1<
b1 Y
0=
b11 X
b1011111111111111 9
b1011111111111111 B
b1011111111111111 Q
b1101 I
b1101 >
b1101 G
b1110 N
b11101 F
b1110 C
b1110 ?
b1110 K
b1110 M
b101110 ;
1:
#92
0:
#93
b1101111111111111 9
b1101111111111111 B
b1101111111111111 Q
b1100 I
b1100 >
b1100 G
b1101 N
b11100 F
b1101 C
b1101 ?
b1101 K
b1101 M
b101111 ;
1:
#94
0:
#95
b1110111111111111 9
b1110111111111111 B
b1110111111111111 Q
b1011 I
b1011 >
b1011 G
b1100 N
b11011 F
b1100 C
b1100 ?
b1100 K
b1100 M
b110000 ;
1:
#96
0:
#97
b1111011111111111 9
b1111011111111111 B
b1111011111111111 Q
b1010 I
b1010 >
b1010 G
b1011 N
b11010 F
b1011 C
b1011 ?
b1011 K
b1011 M
b110001 ;
1:
#98
0:
#99
b1111101111111111 9
b1111101111111111 B
b1111101111111111 Q
b1001 I
b1001 >
b1001 G
b1010 N
b11001 F
b1010 C
b1010 ?
b1010 K
b1010 M
b110010 ;
1:
#100
0:
#101
b1111110111111111 9
b1111110111111111 B
b1111110111111111 Q
b1000 I
b1000 >
b1000 G
b1001 N
b11000 F
b1001 C
b1001 ?
b1001 K
b1001 M
b110011 ;
1:
#102
0:
#103
b1111111011111111 9
b1111111011111111 B
b1111111011111111 Q
b111 I
b111 >
b111 G
b1000 N
b10111 F
b1000 C
b1000 ?
b1000 K
b1000 M
b110100 ;
1:
#104
0:
#105
b1111111101111111 9
b1111111101111111 B
b1111111101111111 Q
b110 I
b110 >
b110 G
b111 N
b10110 F
b111 C
b111 ?
b111 K
b111 M
b110101 ;
1:
#106
0:
#107
b1111111110111111 9
b1111111110111111 B
b1111111110111111 Q
b101 I
b101 >
b101 G
b110 N
b10101 F
b110 C
b110 ?
b110 K
b110 M
b110110 ;
1:
#108
0:
#109
b1111111111011111 9
b1111111111011111 B
b1111111111011111 Q
b100 I
b100 >
b100 G
b101 N
b10100 F
b101 C
b101 ?
b101 K
b101 M
b110111 ;
1:
#110
0:
#111
b1111111111101111 9
b1111111111101111 B
b1111111111101111 Q
b11 I
b11 >
b11 G
b100 N
b10011 F
b100 C
b100 ?
b100 K
b100 M
b111000 ;
1:
#112
0:
#113
b1111111111110111 9
b1111111111110111 B
b1111111111110111 Q
b10 I
b10 >
b10 G
b11 N
b10010 F
b11 C
b11 ?
b11 K
b11 M
b111001 ;
1:
#114
0:
#115
b1111111111111011 9
b1111111111111011 B
b1111111111111011 Q
b1 I
b1 >
b1 G
b10 N
b10001 F
b10 C
b10 ?
b10 K
b10 M
b111010 ;
1:
#116
0:
#117
b1111111111111101 9
b1111111111111101 B
b1111111111111101 Q
b0 I
b0 >
b0 G
b1 N
b10000 F
b1 C
b1 ?
b1 K
b1 M
b111011 ;
1:
#118
0:
#119
b1 D
b1 A
b1 T
b1 V
1@
b1 Z
0<
b11 Y
1=
b1 X
b1 R
b1111111111111110 9
b1111111111111110 B
b1111111111111110 Q
b1 I
b1 >
b1 G
0H
b0 N
b1 F
b0 C
b0 ?
b0 K
b0 M
b111100 ;
1:
#120
0:
#121
0@
b11 Z
1<
b1 Y
0=
b11 X
b1111 R
b1111111111111101 9
b1111111111111101 B
b1111111111111101 Q
b10 I
b10 >
b10 G
b1 N
b10 F
b1 C
b1 ?
b1 K
b1 M
b111101 ;
1:
#122
0:
#123
b1111111111111011 9
b1111111111111011 B
b1111111111111011 Q
b11 I
b11 >
b11 G
b10 N
b11 F
b10 C
b10 ?
b10 K
b10 M
b111110 ;
1:
#124
0:
#125
b1111111111110111 9
b1111111111110111 B
b1111111111110111 Q
b100 I
b100 >
b100 G
b11 N
b100 F
b11 C
b11 ?
b11 K
b11 M
b111111 ;
1:
#126
0:
#127
b1111111111101111 9
b1111111111101111 B
b1111111111101111 Q
b101 I
b101 >
b101 G
b100 N
b101 F
b100 C
b100 ?
b100 K
b100 M
b1000000 ;
1:
