supercar_verilog/L74x04.sv
// 6 port hex inverter
module L74x04
  (
    // Gate 1
    input i_g1,
    output o_g1,

    // Gate 2
    input i_g2,
    output o_g2,
    
    // Gate 3
    input i_g3,
    output o_g3,
    
    // Gate 4
    input i_g4,
    output o_g4,
    
    // Gate 5
    input i_g5,
    output o_g5,
    
    // Gate 6
    input i_g6,
    output o_g6
  );

  assign o_g1 = ~i_g1;
  assign o_g2 = ~i_g2;
  assign o_g3 = ~i_g3;
  assign o_g4 = ~i_g4;
  assign o_g5 = ~i_g5;
  assign o_g6 = ~i_g6;

endmodule

supercar_verilog/L74x02.sv
// 2 port 4 NOR gates
module L74x02
  (
    // Gate 1
    input [1:0] i_g1,
    output o_g1,

    // Gate 2
    input [1:0] i_g2,
    output o_g2,
    
    // Gate 3
    input [1:0] i_g3,
    output o_g3,
    
    // Gate 4
    input [1:0] i_g4,
    output o_g4
  );

  assign o_g1 = ~|i_g1;
  assign o_g2 = ~|i_g2;
  assign o_g3 = ~|i_g3;
  assign o_g4 = ~|i_g4;

endmodule

supercar_verilog/L74x21.sv
// 4-input 2 NAND gates
module L74x21
  (
    // Gate 1
    input [3:0] i_g1,
    output o_g1,

    // Gate 2
    input [3:0] i_g2,
    output o_g2
  );

  assign o_g1 = &i_g1;
  assign o_g2 = &i_g2;
endmodule

supercar_verilog/L74x574.sv
// Octal 3 state non inverting D flip-flop
module L74x574 #(parameter INITIAL_VALUE = 8'h00)
  (
    input [7:0] i_data,
    input i_n_oe,
    input i_clk,
    inout [7:0] o_q
  );

  reg [7:0] r_data = INITIAL_VALUE;

  always @(posedge i_clk)
  begin
    r_data <= i_data;
  end

  assign o_q = i_n_oe ? 8'bZ : r_data;

endmodule

supercar_verilog/L74x154.sv
// 4-to-16 line decoder/demultiplexer
module L74x154
  (
    input [3:0] i_address,
    input i_n_en0,
    input i_n_en1,
    output [15:0] o_selection
  );

  assign o_selection = (i_n_en0 || i_n_en1) ? 16'hFFFF : ~(1'b1 << i_address);

endmodule

supercar_verilog/L74x283.sv
// 4-bit binary full adder with fast carry
module L74x283
  (
    input [3:0] i_a,
    input [3:0] i_b,
    input i_cin,
    output [3:0] o_s,
    output o_cout
  );

  reg [4:0] r_sum;


  assign r_sum = i_a + i_b + i_cin;
  assign o_s = r_sum;
  assign o_cout = r_sum[4];

endmodule

supercar_verilog/Supercar.sv
module SuperCar
  (
    input i_clk,
    output [15:0] o_selection
  );

  wire [3:0] w_sum_result;
  wire [7:0] w_led_address;
  wire [7:0] w_addend;
  wire w_neg_addend;
  wire w_addend_clk;

  wire w_u5_g2_out;
  wire w_u6_g1_out;
  wire w_u6_g2_out;
  wire w_u6_g3_out;

  wire [3:0] w_inverted_led_address;

  L74x283 U1 (
            .i_a(w_led_address[3:0]),
            .i_b(w_addend[3:0]),
            .i_cin(1'b0),
            .o_s(w_sum_result),
            .o_cout() // Left disconnected
          );

  L74x574 U2 (
            .i_data({4'h0, w_sum_result}),
            .i_clk(i_clk),
            .i_n_oe(1'b0),
            .o_q(w_led_address)
          );

  L74x154 U3 (
            .i_address(w_led_address[3:0]), // Only the 4 least significant bits are considered
            .i_n_en0(1'b0),
            .i_n_en1(1'b0),
            .o_selection(o_selection)
          );

  L74x574 #(.INITIAL_VALUE(8'hFF)) U4 (
            .i_data({4'h0, {3{w_neg_addend}}, 1'b1}),
            .i_clk(w_addend_clk),
            .i_n_oe(1'b0),
            .o_q(w_addend)
          );

  L74x21 U5 (
           .i_g1(w_led_address[3:0]),
           .o_g1(w_neg_addend),
           .i_g2(w_inverted_led_address),
           .o_g2(w_u5_g2_out)
         );

  L74x02 U6 (
           .i_g1({w_neg_addend, w_u5_g2_out}),
           .o_g1(w_u6_g1_out),
           .i_g2({w_u6_g1_out, w_u6_g1_out}),
           .o_g2(w_u6_g2_out),
           .i_g3({w_u6_g2_out, w_u6_g2_out}),
           .o_g3(w_u6_g3_out),
           .i_g4({w_u6_g3_out, w_u6_g3_out}),
           .o_g4(w_addend_clk)
         );

  L74x04 U7 (
           .i_g1(w_led_address[0]),
           .o_g1(w_inverted_led_address[0]),
           .i_g2(w_led_address[1]),
           .o_g2(w_inverted_led_address[1]),
           .i_g3(w_led_address[2]),
           .o_g3(w_inverted_led_address[2]),
           .i_g4(w_led_address[3]),
           .o_g4(w_inverted_led_address[3]),
           .i_g5(1'b0),
           .o_g5(),
           .i_g6(1'b0),
           .o_g6()
         );

endmodule

supercar_verilog/testbench.vh
module Testbench_SuperCar();
  reg r_clk = 1'b0; // This will be used as clock
  wire [15:0] w_selection;
  integer i;

  // Use this always block to generate a clock
  // by inverting this register every time unit,
  // so a full clock cycle takes 2 time units
  always #1 r_clk <= !r_clk;

  SuperCar UUT (
    .i_clk(r_clk),
    .o_selection(w_selection)
  );

  initial
  begin
    $dumpfile("dump.vcd");
    $dumpvars;

    for(i = 0; i < 64; i = i + 1)
    begin
      @(posedge r_clk);
    end

    $display("Test Complete");
    $finish();
  end
endmodule

supercar_verilog/dump.vcd
$date
	Thu Jan 25 20:35:52 2024
$end
$version
	Icarus Verilog
$end
$timescale
	1s
$end
$scope module Testbench_SuperCar $end
$var wire 16 ! w_selection [15:0] $end
$var reg 1 " r_clk $end
$var integer 32 # i [31:0] $end
$scope module UUT $end
$var wire 1 " i_clk $end
$var wire 1 $ w_u6_g3_out $end
$var wire 1 % w_u6_g2_out $end
$var wire 1 & w_u6_g1_out $end
$var wire 1 ' w_u5_g2_out $end
$var wire 4 ( w_sum_result [3:0] $end
$var wire 1 ) w_neg_addend $end
$var wire 8 * w_led_address [7:0] $end
$var wire 4 + w_inverted_led_address [3:0] $end
$var wire 1 , w_addend_clk $end
$var wire 8 - w_addend [7:0] $end
$var wire 16 . o_selection [15:0] $end
$scope module U1 $end
$var wire 4 / i_a [3:0] $end
$var wire 4 0 i_b [3:0] $end
$var wire 1 1 i_cin $end
$var wire 5 2 r_sum [4:0] $end
$var wire 4 3 o_s [3:0] $end
$var wire 1 4 o_cout $end
$upscope $end
$scope module U2 $end
$var wire 1 " i_clk $end
$var wire 8 5 i_data [7:0] $end
$var wire 1 6 i_n_oe $end
$var wire 8 7 o_q [7:0] $end
$var parameter 8 8 INITIAL_VALUE $end
$var reg 8 9 r_data [7:0] $end
$upscope $end
$scope module U3 $end
$var wire 4 : i_address [3:0] $end
$var wire 1 ; i_n_en0 $end
$var wire 1 < i_n_en1 $end
$var wire 16 = o_selection [15:0] $end
$upscope $end
$scope module U4 $end
$var wire 8 > i_data [7:0] $end
$var wire 1 ? i_n_oe $end
$var wire 8 @ o_q [7:0] $end
$var wire 1 , i_clk $end
$var parameter 8 A INITIAL_VALUE $end
$var reg 8 B r_data [7:0] $end
$upscope $end
$scope module U5 $end
$var wire 4 C i_g1 [3:0] $end
$var wire 4 D i_g2 [3:0] $end
$var wire 1 ' o_g2 $end
$var wire 1 ) o_g1 $end
$upscope $end
$scope module U6 $end
$var wire 2 E i_g1 [1:0] $end
$var wire 2 F i_g2 [1:0] $end
$var wire 2 G i_g3 [1:0] $end
$var wire 2 H i_g4 [1:0] $end
$var wire 1 , o_g4 $end
$var wire 1 $ o_g3 $end
$var wire 1 % o_g2 $end
$var wire 1 & o_g1 $end
$upscope $end
$scope module U7 $end
$var wire 1 I i_g1 $end
$var wire 1 J i_g2 $end
$var wire 1 K i_g3 $end
$var wire 1 L i_g4 $end
$var wire 1 M i_g5 $end
$var wire 1 N i_g6 $end
$var wire 1 O o_g1 $end
$var wire 1 P o_g2 $end
$var wire 1 Q o_g3 $end
$var wire 1 R o_g4 $end
$var wire 1 S o_g5 $end
$var wire 1 T o_g6 $end
$upscope $end
$upscope $end
$upscope $end
$enddefinitions $end
$comment Show the parameter values. $end
$dumpall
b11111111 A
b0 8
$end
#0
$dumpvars
1T
1S
1R
1Q
1P
1O
0N
0M
0L
0K
0J
0I
b0 H
b11 G
b0 F
b1 E
b1111 D
b0 C
b11111111 B
b11111111 @
0?
b1 >
b1111111111111110 =
0<
0;
b0 :
b0 9
b0 7
06
b1111 5
04
b1111 3
b1111 2
01
b1111 0
b0 /
b1111111111111110 .
b11111111 -
1,
b1111 +
b0 *
0)
b1111 (
1'
0&
1%
0$
b0 #
0"
b1111111111111110 !
$end
#1
b111111111111111 !
b111111111111111 .
b111111111111111 =
0R
0Q
0P
0'
b0 +
b0 D
0O
b1110 5
b1110 (
b1110 3
14
1L
1K
1J
1I
b10 E
b1111 >
1)
b1111 C
b1111 :
b11110 2
b1111 /
b1111 *
b1111 7
b1111 9
b1 #
1"
#2
0"
#3
b1011111111111111 !
b1011111111111111 .
b1011111111111111 =
b1 +
b1 D
1O
b1101 5
b1101 (
b1101 3
0I
0,
b11 H
1$
b0 G
0%
b11 F
1&
b0 E
b1 >
0)
b1110 C
b1110 :
b11101 2
b1110 /
b1110 *
b1110 7
b1110 9
b10 #
1"
#4
0"
#5
b1101111111111111 !
b1101111111111111 .
b1101111111111111 =
1P
b10 +
b10 D
0O
b1100 5
b1100 (
b1100 3
0J
1I
b1101 C
b1101 :
b11100 2
b1101 /
b1101 *
b1101 7
b1101 9
b11 #
1"
#6
0"
#7
b1110111111111111 !
b1110111111111111 .
b1110111111111111 =
b11 +
b11 D
1O
b1011 5
b1011 (
b1011 3
0I
b1100 C
b1100 :
b11011 2
b1100 /
b1100 *
b1100 7
b1100 9
b100 #
1"
#8
0"
#9
b1111011111111111 !
b1111011111111111 .
b1111011111111111 =
1Q
0P
b100 +
b100 D
0O
b1010 5
b1010 (
b1010 3
0K
1J
1I
b1011 C
b1011 :
b11010 2
b1011 /
b1011 *
b1011 7
b1011 9
b101 #
1"
#10
0"
#11
b1111101111111111 !
b1111101111111111 .
b1111101111111111 =
b101 +
b101 D
1O
b1001 5
b1001 (
b1001 3
0I
b1010 C
b1010 :
b11001 2
b1010 /
b1010 *
b1010 7
b1010 9
b110 #
1"
#12
0"
#13
b1111110111111111 !
b1111110111111111 .
b1111110111111111 =
1P
b110 +
b110 D
0O
b1000 5
b1000 (
b1000 3
0J
1I
b1001 C
b1001 :
b11000 2
b1001 /
b1001 *
b1001 7
b1001 9
b111 #
1"
#14
0"
#15
b1111111011111111 !
b1111111011111111 .
b1111111011111111 =
b111 +
b111 D
1O
b111 5
b111 (
b111 3
0I
b1000 C
b1000 :
b10111 2
b1000 /
b1000 *
b1000 7
b1000 9
b1000 #
1"
#16
0"
#17
b1111111101111111 !
b1111111101111111 .
b1111111101111111 =
1R
0Q
0P
b1000 +
b1000 D
0O
b110 5
b110 (
b110 3
0L
1K
1J
1I
b111 C
b111 :
b10110 2
b111 /
b111 *
b111 7
b111 9
b1001 #
1"
#18
0"
#19
b1111111110111111 !
b1111111110111111 .
b1111111110111111 =
b1001 +
b1001 D
1O
b101 5
b101 (
b101 3
0I
b110 C
b110 :
b10101 2
b110 /
b110 *
b110 7
b110 9
b1010 #
1"
#20
0"
#21
b1111111111011111 !
b1111111111011111 .
b1111111111011111 =
1P
b1010 +
b1010 D
0O
b100 5
b100 (
b100 3
0J
1I
b101 C
b101 :
b10100 2
b101 /
b101 *
b101 7
b101 9
b1011 #
1"
#22
0"
#23
b1111111111101111 !
b1111111111101111 .
b1111111111101111 =
b1011 +
b1011 D
1O
b11 5
b11 (
b11 3
0I
b100 C
b100 :
b10011 2
b100 /
b100 *
b100 7
b100 9
b1100 #
1"
#24
0"
#25
b1111111111110111 !
b1111111111110111 .
b1111111111110111 =
1Q
0P
b1100 +
b1100 D
0O
b10 5
b10 (
b10 3
0K
1J
1I
b11 C
b11 :
b10010 2
b11 /
b11 *
b11 7
b11 9
b1101 #
1"
#26
0"
#27
b1111111111111011 !
b1111111111111011 .
b1111111111111011 =
b1101 +
b1101 D
1O
b1 5
b1 (
b1 3
0I
b10 C
b10 :
b10001 2
b10 /
b10 *
b10 7
b10 9
b1110 #
1"
#28
0"
#29
b1111111111111101 !
b1111111111111101 .
b1111111111111101 =
1P
b1110 +
b1110 D
0O
b0 5
b0 (
b0 3
0J
1I
b1 C
b1 :
b10000 2
b1 /
b1 *
b1 7
b1 9
b1111 #
1"
#30
0"
#31
b1 0
b1 -
b1 @
b1 B
b1111111111111110 !
b1111111111111110 .
b1111111111111110 =
1,
b0 H
0$
b11 G
1%
b0 F
0&
b1 E
1'
b1111 +
b1111 D
1O
b1 5
b1 (
b1 3
04
0I
b0 C
b0 :
b1 2
b0 /
b0 *
b0 7
b0 9
b10000 #
1"
#32
0"
#33
b1111111111111101 !
b1111111111111101 .
b1111111111111101 =
0,
b11 H
1$
b0 G
0%
b11 F
1&
b0 E
0'
b1110 +
b1110 D
0O
b10 5
b10 (
b10 3
1I
b1 C
b1 :
b10 2
b1 /
b1 *
b1 7
b1 9
b10001 #
1"
#34
0"
#35
b1111111111111011 !
b1111111111111011 .
b1111111111111011 =
0P
0,
b11 H
1$
b0 G
0%
b11 F
1&
b0 E
0'
b1101 +
b1101 D
1O
b11 5
b11 (
b11 3
1J
0I
b10 C
b10 :
b11 2
b10 /
b10 *
b10 7
b10 9
b10010 #
1"
#36
0"
#37
b1111111111110111 !
b1111111111110111 .
b1111111111110111 =
b1100 +
b1100 D
0O
b100 5
b100 (
b100 3
1I
b11 C
b11 :
b100 2
b11 /
b11 *
b11 7
b11 9
b10011 #
1"
#38
0"
#39
b1111111111101111 !
b1111111111101111 .
b1111111111101111 =
0Q
0,
b11 H
1$
b0 G
0%
b11 F
1&
b0 E
0'
1P
b1011 +
b1011 D
1O
b101 5
b101 (
b101 3
1K
0J
0I
b100 C
b100 :
b101 2
b100 /
b100 *
b100 7
b100 9
b10100 #
1"
#40
0"
#41
b1111111111011111 !
b1111111111011111 .
b1111111111011111 =
b1010 +
b1010 D
0O
b110 5
b110 (
b110 3
1I
b101 C
b101 :
b110 2
b101 /
b101 *
b101 7
b101 9
b10101 #
1"
#42
0"
#43
b1111111110111111 !
b1111111110111111 .
b1111111110111111 =
0P
b1001 +
b1001 D
1O
b111 5
b111 (
b111 3
1J
0I
b110 C
b110 :
b111 2
b110 /
b110 *
b110 7
b110 9
b10110 #
1"
#44
0"
#45
b1111111101111111 !
b1111111101111111 .
b1111111101111111 =
b1000 +
b1000 D
0O
b1000 5
b1000 (
b1000 3
1I
b111 C
b111 :
b1000 2
b111 /
b111 *
b111 7
b111 9
b10111 #
1"
#46
0"
#47
b1111111011111111 !
b1111111011111111 .
b1111111011111111 =
0R
0,
b11 H
1$
b0 G
0%
b11 F
1&
b0 E
0'
1Q
1P
b111 +
b111 D
1O
b1001 5
b1001 (
b1001 3
1L
0K
0J
0I
b1000 C
b1000 :
b1001 2
b1000 /
b1000 *
b1000 7
b1000 9
b11000 #
1"
#48
0"
#49
b1111110111111111 !
b1111110111111111 .
b1111110111111111 =
b110 +
b110 D
0O
b1010 5
b1010 (
b1010 3
1I
b1001 C
b1001 :
b1010 2
b1001 /
b1001 *
b1001 7
b1001 9
b11001 #
1"
#50
0"
#51
b1111101111111111 !
b1111101111111111 .
b1111101111111111 =
0P
b101 +
b101 D
1O
b1011 5
b1011 (
b1011 3
1J
0I
b1010 C
b1010 :
b1011 2
b1010 /
b1010 *
b1010 7
b1010 9
b11010 #
1"
#52
0"
#53
b1111011111111111 !
b1111011111111111 .
b1111011111111111 =
b100 +
b100 D
0O
b1100 5
b1100 (
b1100 3
1I
b1011 C
b1011 :
b1100 2
b1011 /
b1011 *
b1011 7
b1011 9
b11011 #
1"
#54
0"
#55
b1110111111111111 !
b1110111111111111 .
b1110111111111111 =
0Q
1P
b11 +
b11 D
1O
b1101 5
b1101 (
b1101 3
1K
0J
0I
b1100 C
b1100 :
b1101 2
b1100 /
b1100 *
b1100 7
b1100 9
b11100 #
1"
#56
0"
#57
b1101111111111111 !
b1101111111111111 .
b1101111111111111 =
b10 +
b10 D
0O
b1110 5
b1110 (
b1110 3
1I
b1101 C
b1101 :
b1110 2
b1101 /
b1101 *
b1101 7
b1101 9
b11101 #
1"
#58
0"
#59
b1011111111111111 !
b1011111111111111 .
b1011111111111111 =
0P
b1 +
b1 D
1O
b1111 5
b1111 (
b1111 3
1J
0I
b1110 C
b1110 :
b1111 2
b1110 /
b1110 *
b1110 7
b1110 9
b11110 #
1"
#60
0"
#61
b1111 0
b1111 -
b1111 @
b1111 B
b111111111111111 !
b111111111111111 .
b111111111111111 =
b0 +
b0 D
0O
b1110 5
b1110 (
b1110 3
14
1I
1,
b0 H
0$
b11 G
1%
b0 F
0&
b10 E
b1111 >
1)
b1111 C
b1111 :
b11110 2
b1111 /
b1111 *
b1111 7
b1111 9
b11111 #
1"
#62
0"
#63
b1011111111111111 !
b1011111111111111 .
b1011111111111111 =
b1 +
b1 D
1O
b1101 5
b1101 (
b1101 3
0I
0,
b11 H
1$
b0 G
0%
b11 F
1&
b0 E
b1 >
0)
b1110 C
b1110 :
b11101 2
b1110 /
b1110 *
b1110 7
b1110 9
b100000 #
1"
#64
0"
#65
b1101111111111111 !
b1101111111111111 .
b1101111111111111 =
1P
b10 +
b10 D
0O
b1100 5
b1100 (
b1100 3
0J
1I
b1101 C
b1101 :
b11100 2
b1101 /
b1101 *
b1101 7
b1101 9
b100001 #
1"
#66
0"
#67
b1110111111111111 !
b1110111111111111 .
b1110111111111111 =
b11 +
b11 D
1O
b1011 5
b1011 (
b1011 3
0I
b1100 C
b1100 :
b11011 2
b1100 /
b1100 *
b1100 7
b1100 9
b100010 #
1"
#68
0"
#69
b1111011111111111 !
b1111011111111111 .
b1111011111111111 =
1Q
0P
b100 +
b100 D
0O
b1010 5
b1010 (
b1010 3
0K
1J
1I
b1011 C
b1011 :
b11010 2
b1011 /
b1011 *
b1011 7
b1011 9
b100011 #
1"
#70
0"
#71
b1111101111111111 !
b1111101111111111 .
b1111101111111111 =
b101 +
b101 D
1O
b1001 5
b1001 (
b1001 3
0I
b1010 C
b1010 :
b11001 2
b1010 /
b1010 *
b1010 7
b1010 9
b100100 #
1"
#72
0"
#73
b1111110111111111 !
b1111110111111111 .
b1111110111111111 =
1P
b110 +
b110 D
0O
b1000 5
b1000 (
b1000 3
0J
1I
b1001 C
b1001 :
b11000 2
b1001 /
b1001 *
b1001 7
b1001 9
b100101 #
1"
#74
0"
#75
b1111111011111111 !
b1111111011111111 .
b1111111011111111 =
b111 +
b111 D
1O
b111 5
b111 (
b111 3
0I
b1000 C
b1000 :
b10111 2
b1000 /
b1000 *
b1000 7
b1000 9
b100110 #
1"
#76
0"
#77
b1111111101111111 !
b1111111101111111 .
b1111111101111111 =
1R
0Q
0P
b1000 +
b1000 D
0O
b110 5
b110 (
b110 3
0L
1K
1J
1I
b111 C
b111 :
b10110 2
b111 /
b111 *
b111 7
b111 9
b100111 #
1"
#78
0"
#79
b1111111110111111 !
b1111111110111111 .
b1111111110111111 =
b1001 +
b1001 D
1O
b101 5
b101 (
b101 3
0I
b110 C
b110 :
b10101 2
b110 /
b110 *
b110 7
b110 9
b101000 #
1"
#80
0"
#81
b1111111111011111 !
b1111111111011111 .
b1111111111011111 =
1P
b1010 +
b1010 D
0O
b100 5
b100 (
b100 3
0J
1I
b101 C
b101 :
b10100 2
b101 /
b101 *
b101 7
b101 9
b101001 #
1"
#82
0"
#83
b1111111111101111 !
b1111111111101111 .
b1111111111101111 =
b1011 +
b1011 D
1O
b11 5
b11 (
b11 3
0I
b100 C
b100 :
b10011 2
b100 /
b100 *
b100 7
b100 9
b101010 #
1"
#84
0"
#85
b1111111111110111 !
b1111111111110111 .
b1111111111110111 =
1Q
0P
b1100 +
b1100 D
0O
b10 5
b10 (
b10 3
0K
1J
1I
b11 C
b11 :
b10010 2
b11 /
b11 *
b11 7
b11 9
b101011 #
1"
#86
0"
#87
b1111111111111011 !
b1111111111111011 .
b1111111111111011 =
b1101 +
b1101 D
1O
b1 5
b1 (
b1 3
0I
b10 C
b10 :
b10001 2
b10 /
b10 *
b10 7
b10 9
b101100 #
1"
#88
0"
#89
b1111111111111101 !
b1111111111111101 .
b1111111111111101 =
1P
b1110 +
b1110 D
0O
b0 5
b0 (
b0 3
0J
1I
b1 C
b1 :
b10000 2
b1 /
b1 *
b1 7
b1 9
b101101 #
1"
#90
0"
#91
b1 0
b1 -
b1 @
b1 B
b1111111111111110 !
b1111111111111110 .
b1111111111111110 =
1,
b0 H
0$
b11 G
1%
b0 F
0&
b1 E
1'
b1111 +
b1111 D
1O
b1 5
b1 (
b1 3
04
0I
b0 C
b0 :
b1 2
b0 /
b0 *
b0 7
b0 9
b101110 #
1"
#92
0"
#93
b1111111111111101 !
b1111111111111101 .
b1111111111111101 =
0,
b11 H
1$
b0 G
0%
b11 F
1&
b0 E
0'
b1110 +
b1110 D
0O
b10 5
b10 (
b10 3
1I
b1 C
b1 :
b10 2
b1 /
b1 *
b1 7
b1 9
b101111 #
1"
#94
0"
#95
b1111111111111011 !
b1111111111111011 .
b1111111111111011 =
0P
0,
b11 H
1$
b0 G
0%
b11 F
1&
b0 E
0'
b1101 +
b1101 D
1O
b11 5
b11 (
b11 3
1J
0I
b10 C
b10 :
b11 2
b10 /
b10 *
b10 7
b10 9
b110000 #
1"
#96
0"
#97
b1111111111110111 !
b1111111111110111 .
b1111111111110111 =
b1100 +
b1100 D
0O
b100 5
b100 (
b100 3
1I
b11 C
b11 :
b100 2
b11 /
b11 *
b11 7
b11 9
b110001 #
1"
#98
0"
#99
b1111111111101111 !
b1111111111101111 .
b1111111111101111 =
0Q
0,
b11 H
1$
b0 G
0%
b11 F
1&
b0 E
0'
1P
b1011 +
b1011 D
1O
b101 5
b101 (
b101 3
1K
0J
0I
b100 C
b100 :
b101 2
b100 /
b100 *
b100 7
b100 9
b110010 #
1"
#100
0"
#101
b1111111111011111 !
b1111111111011111 .
b1111111111011111 =
b1010 +
b1010 D
0O
b110 5
b110 (
b110 3
1I
b101 C
b101 :
b110 2
b101 /
b101 *
b101 7
b101 9
b110011 #
1"
#102
0"
#103
b1111111110111111 !
b1111111110111111 .
b1111111110111111 =
0P
b1001 +
b1001 D
1O
b111 5
b111 (
b111 3
1J
0I
b110 C
b110 :
b111 2
b110 /
b110 *
b110 7
b110 9
b110100 #
1"
#104
0"
#105
b1111111101111111 !
b1111111101111111 .
b1111111101111111 =
b1000 +
b1000 D
0O
b1000 5
b1000 (
b1000 3
1I
b111 C
b111 :
b1000 2
b111 /
b111 *
b111 7
b111 9
b110101 #
1"
#106
0"
#107
b1111111011111111 !
b1111111011111111 .
b1111111011111111 =
0R
0,
b11 H
1$
b0 G
0%
b11 F
1&
b0 E
0'
1Q
1P
b111 +
b111 D
1O
b1001 5
b1001 (
b1001 3
1L
0K
0J
0I
b1000 C
b1000 :
b1001 2
b1000 /
b1000 *
b1000 7
b1000 9
b110110 #
1"
#108
0"
#109
b1111110111111111 !
b1111110111111111 .
b1111110111111111 =
b110 +
b110 D
0O
b1010 5
b1010 (
b1010 3
1I
b1001 C
b1001 :
b1010 2
b1001 /
b1001 *
b1001 7
b1001 9
b110111 #
1"
#110
0"
#111
b1111101111111111 !
b1111101111111111 .
b1111101111111111 =
0P
b101 +
b101 D
1O
b1011 5
b1011 (
b1011 3
1J
0I
b1010 C
b1010 :
b1011 2
b1010 /
b1010 *
b1010 7
b1010 9
b111000 #
1"
#112
0"
#113
b1111011111111111 !
b1111011111111111 .
b1111011111111111 =
b100 +
b100 D
0O
b1100 5
b1100 (
b1100 3
1I
b1011 C
b1011 :
b1100 2
b1011 /
b1011 *
b1011 7
b1011 9
b111001 #
1"
#114
0"
#115
b1110111111111111 !
b1110111111111111 .
b1110111111111111 =
0Q
1P
b11 +
b11 D
1O
b1101 5
b1101 (
b1101 3
1K
0J
0I
b1100 C
b1100 :
b1101 2
b1100 /
b1100 *
b1100 7
b1100 9
b111010 #
1"
#116
0"
#117
b1101111111111111 !
b1101111111111111 .
b1101111111111111 =
b10 +
b10 D
0O
b1110 5
b1110 (
b1110 3
1I
b1101 C
b1101 :
b1110 2
b1101 /
b1101 *
b1101 7
b1101 9
b111011 #
1"
#118
0"
#119
b1011111111111111 !
b1011111111111111 .
b1011111111111111 =
0P
b1 +
b1 D
1O
b1111 5
b1111 (
b1111 3
1J
0I
b1110 C
b1110 :
b1111 2
b1110 /
b1110 *
b1110 7
b1110 9
b111100 #
1"
#120
0"
#121
b1111 0
b1111 -
b1111 @
b1111 B
b111111111111111 !
b111111111111111 .
b111111111111111 =
b0 +
b0 D
0O
b1110 5
b1110 (
b1110 3
14
1I
1,
b0 H
0$
b11 G
1%
b0 F
0&
b10 E
b1111 >
1)
b1111 C
b1111 :
b11110 2
b1111 /
b1111 *
b1111 7
b1111 9
b111101 #
1"
#122
0"
#123
b1011111111111111 !
b1011111111111111 .
b1011111111111111 =
b1 +
b1 D
1O
b1101 5
b1101 (
b1101 3
0I
0,
b11 H
1$
b0 G
0%
b11 F
1&
b0 E
b1 >
0)
b1110 C
b1110 :
b11101 2
b1110 /
b1110 *
b1110 7
b1110 9
b111110 #
1"
#124
0"
#125
b1101111111111111 !
b1101111111111111 .
b1101111111111111 =
1P
b10 +
b10 D
0O
b1100 5
b1100 (
b1100 3
0J
1I
b1101 C
b1101 :
b11100 2
b1101 /
b1101 *
b1101 7
b1101 9
b111111 #
1"
#126
0"
#127
b1110111111111111 !
b1110111111111111 .
b1110111111111111 =
b11 +
b11 D
1O
b1011 5
b1011 (
b1011 3
0I
b1100 C
b1100 :
b11011 2
b1100 /
b1100 *
b1100 7
b1100 9
b1000000 #
1"
